[
  {
    "ContainingType": "TicketSystem.API.Controllers.AuthController",
    "Method": "Login",
    "RelativePath": "api/Auth/Login",
    "HttpMethod": "POST",
    "IsController": true,
    "Order": 0,
    "Parameters": [
      {
        "Name": "Request",
        "Type": "TicketSystem.API.Models.LoginRequest",
        "IsRequired": true
      }
    ],
    "ReturnTypes": []
  },
  {
    "ContainingType": "TicketSystem.API.Controllers.TicketesController",
    "Method": "AssignTicket",
    "RelativePath": "api/Ticketes/assign",
    "HttpMethod": "PUT",
    "IsController": true,
    "Order": 0,
    "Parameters": [
      {
        "Name": "request",
        "Type": "TicketSystem.API.Models.AssignTicketRequest",
        "IsRequired": true
      }
    ],
    "ReturnTypes": []
  },
  {
    "ContainingType": "TicketSystem.API.Controllers.TicketesController",
    "Method": "AddComment",
    "RelativePath": "api/Ticketes/comment",
    "HttpMethod": "POST",
    "IsController": true,
    "Order": 0,
    "Parameters": [
      {
        "Name": "request",
        "Type": "TicketSystem.API.Models.AddCommentRequest",
        "IsRequired": true
      }
    ],
    "ReturnTypes": []
  },
  {
    "ContainingType": "TicketSystem.API.Controllers.TicketesController",
    "Method": "GetComments",
    "RelativePath": "api/Ticketes/comments/{ticketId}",
    "HttpMethod": "GET",
    "IsController": true,
    "Order": 0,
    "Parameters": [
      {
        "Name": "ticketId",
        "Type": "System.Int32",
        "IsRequired": true
      }
    ],
    "ReturnTypes": []
  },
  {
    "ContainingType": "TicketSystem.API.Controllers.TicketesController",
    "Method": "creteticket",
    "RelativePath": "api/Ticketes/create",
    "HttpMethod": "POST",
    "IsController": true,
    "Order": 0,
    "Parameters": [
      {
        "Name": "model",
        "Type": "TicketSystem.API.Models.CreateTicket",
        "IsRequired": true
      }
    ],
    "ReturnTypes": []
  },
  {
    "ContainingType": "TicketSystem.API.Controllers.TicketesController",
    "Method": "GetTickets",
    "RelativePath": "api/Ticketes/list",
    "HttpMethod": "GET",
    "IsController": true,
    "Order": 0,
    "Parameters": [
      {
        "Name": "UserId",
        "Type": "System.Int32",
        "IsRequired": false
      },
      {
        "Name": "Role",
        "Type": "System.String",
        "IsRequired": false
      }
    ],
    "ReturnTypes": []
  },
  {
    "ContainingType": "TicketSystem.API.Controllers.TicketesController",
    "Method": "UpdateStatus",
    "RelativePath": "api/Ticketes/status",
    "HttpMethod": "PUT",
    "IsController": true,
    "Order": 0,
    "Parameters": [
      {
        "Name": "ticketId",
        "Type": "System.Int32",
        "IsRequired": false
      },
      {
        "Name": "newStatus",
        "Type": "System.String",
        "IsRequired": false
      },
      {
        "Name": "updatedBy",
        "Type": "System.String",
        "IsRequired": false
      }
    ],
    "ReturnTypes": []
  },
  {
    "ContainingType": "TicketSystem.API.Controllers.WeatherForecastController",
    "Method": "Get",
    "RelativePath": "WeatherForecast",
    "HttpMethod": "GET",
    "IsController": true,
    "Order": 0,
    "Parameters": [],
    "ReturnTypes": [
      {
        "Type": "System.Collections.Generic.IEnumerable\u00601[[TicketSystem.API.WeatherForecast, TicketSystem.API, Version=1.0.0.0, Culture=neutral, PublicKeyToken=null]]",
        "MediaTypes": [
          "text/plain",
          "application/json",
          "text/json"
        ],
        "StatusCode": 200
      }
    ],
    "EndpointName": "GetWeatherForecast"
  }
]